db/SQLException.py
db/__init__.py
db/pypostgres.py
utils/AbstractException.py
utils/__init__.py
utils/utils.py
libpyka-0.1.18.dist-info/LICENSE.txt
libpyka-0.1.18.dist-info/METADATA
libpyka-0.1.18.dist-info/WHEEL
libpyka-0.1.18.dist-info/top_level.txt
libpyka-0.1.18.dist-info/RECORD
