Metadata-Version: 2.1
Name: libpyka
Version: 0.1.18
Summary: Pythonの一般的ユーティリティーライブラリ
Home-page: https://github.com/karakawa88/libpyka/
Author: Kentarou Arakawa
Author-email: kagalpan@kacpp.xyz
License: UNKNOWN
Platform: UNKNOWN
Classifier: License :: OSI Approved :: MIT License
Classifier: Programming Language :: Python :: 3
Classifier: Programming Language :: Python :: 3.6
Classifier: Programming Language :: Python :: 3.7
Classifier: Programming Language :: Python :: 3.8
Classifier: Operating System :: OS Independent
Requires-Python: ~=3.6
Requires-Dist: beautifulsoup4 (>=4.9.*)
Requires-Dist: chardet (>=4.*)
Requires-Dist: cssselect (>=1.*)
Requires-Dist: psycopg2 (>=2.8.6)
Requires-Dist: requests (>=2.*)
Requires-Dist: types-chardet (>=0.*)
Requires-Dist: types-requests (>=0.1.*)
